mactime/__init__.py
mactime/__main__.py
mactime/_cli_interface.py
mactime/cli.py
mactime/constants.py
mactime/core.py
mactime/errors.py
mactime/logger.py
mactime/utils.py
mactime/vendored/__init__.py
mactime/vendored/argparse_color_formatter.py
mactime-0.1.0.dist-info/METADATA
mactime-0.1.0.dist-info/WHEEL
mactime-0.1.0.dist-info/entry_points.txt
mactime-0.1.0.dist-info/RECORD
