Metadata-Version: 2.4
Name: mactime
Version: 0.1.0
Summary: Take control over macOS files timestamps.
Project-URL: Homepage, https://github.com/Bobronium/mactime
Project-URL: Repository, https://github.com/Bobronium/mactime.git
Project-URL: Issues, https://github.com/Bobronium/mactime/issues
Author: Claude.ai
Author-email: Arseny Boykov <hi@bobronium.me>
Requires-Python: >=3.9
Provides-Extra: dev
Requires-Dist: mypy>=1.15.0; extra == 'dev'
Requires-Dist: pyinstrument>=5.0.1; extra == 'dev'
Requires-Dist: pyright>=1.1.394; extra == 'dev'
Requires-Dist: pytest-cov>=6.0.0; extra == 'dev'
Requires-Dist: pytest>=8.3.4; extra == 'dev'
Requires-Dist: ruff>=0.9.7; extra == 'dev'
Provides-Extra: lint
Requires-Dist: ruff>=0.9.7; extra == 'lint'
Provides-Extra: profile
Requires-Dist: pyinstrument>=5.0.1; extra == 'profile'
Provides-Extra: test
Requires-Dist: pytest-cov>=6.0.0; extra == 'test'
Requires-Dist: pytest>=8.3.4; extra == 'test'
Provides-Extra: typecheck
Requires-Dist: mypy>=1.15.0; extra == 'typecheck'
Requires-Dist: pyright>=1.1.394; extra == 'typecheck'
